netdevice/__init__.py
netdevice/cisco.py
netdevice/junos.py
netdevice/linux.py
netdevice/ovn.py
netdevice/ovs.py
netdevice/webpage.py
netdevice-1.3.6.data/scripts/demo.py
netdevice-1.3.6.dist-info/METADATA
netdevice-1.3.6.dist-info/WHEEL
netdevice-1.3.6.dist-info/top_level.txt
netdevice-1.3.6.dist-info/RECORD
