Metadata-Version: 2.4
Name: netdevice
Version: 1.3.6
Summary: Python modules to execute command on remote network device based on pexpect.
Home-page: https://github.com/guoyoooping/networkdevice
Author: Yongping Guo
Author-email: Yongping Guo <guoyoooping@163.com>
License: GPLv3
Project-URL: Homepage, https://github.com/guoyoooping/networkdevice
Keywords: pexpect,netdevice
Requires-Dist: Pillow>=3.0.0
Requires-Dist: ipaddress
Requires-Dist: pexpect
Requires-Dist: lxml
Requires-Dist: IPy
Requires-Dist: xmltodict
Requires-Dist: dpkt
Requires-Dist: simplejson
Dynamic: author
Dynamic: home-page
